[
    {"pk": 1, "model": "products.product", "fields": {"sku": "pp5001340155", "name": "Toilet Brush", "description": "Brabantia Brilliant Steel Toilet Brush & Holder", "quantity": "1",  "price": 16.99, "category": 12, "rating": 4.5, "image_url": "http://s7d9.scene7.com/is/image/JCPenney/DP0709201205510679M.tif?hei=380&amp;wid=380&op_usm=.4,.8,0,0&resmode=sharp2&op_usm=1.5,.8,0,0&resmode=sharp", "image": "toilet_brush.jpg"}}, 
    {"pk": 2, "model": "products.product", "fields": {"sku": "pp5001600425", "name": "Gin Glass", "description": "Juniper Gin Balloon Glass 72cl (25oz)", "quantity": "24", "price": 58.99, "category": 10, "rating": 4.2, "image_url": "http://s7d9.scene7.com/is/image/JCPenney/DP0113201617034987M.tif?hei=380&amp;wid=380&op_usm=.4,.8,0,0&resmode=sharp2&op_usm=1.5,.8,0,0&resmode=sharp", "image": "gin_glass.jpg"}}, 
    {"pk": 3, "model": "products.product", "fields": {"sku": "pp5001730010", "name": "Brasso", "description": "Brasso Metal polish 1ltr", "quantity": "1", "price": 12.99, "category": 2, "rating": 4.7, "image_url": "http://s7d9.scene7.com/is/image/JCPenney/DP1230201417013175M.tif?hei=380&amp;wid=380&op_usm=.4,.8,0,0&resmode=sharp2&op_usm=1.5,.8,0,0&resmode=sharp", "image": "brasso.jpg"}}, 
    {"pk": 4, "model": "products.product", "fields": {"sku": "pp5001890157", "name": "Taski R2", "description": "Taski R2 Multi Surface Cleaner", "quantity": "6", "price": 16.99, "category": 2, "rating": 4.7, "image_url": "http://s7d9.scene7.com/is/image/JCPenney/DP0716201503423610M.tif?hei=380&amp;wid=380&op_usm=.4,.8,0,0&resmode=sharp2&op_usm=1.5,.8,0,0&resmode=sharp", "image": "r2_spray.jpg"}}, 
    {"pk": 5, "model": "products.product", "fields": {"sku": "pp5002111605", "name": "Taski R3", "description": "Taski R3", "quantity": "6", "price": 29.99, "category": 2, "rating": 4.1, "image_url": "http://s7d9.scene7.com/is/image/JCPenney/DP1115201210371197C.tif?hei=380&amp;wid=380&op_usm=.4,.8,0,0&resmode=sharp2&op_usm=1.5,.8,0,0&resmode=sharp", "image": "r3_spray.jpg"}}, 
    {"pk": 6, "model": "products.product", "fields": {"sku": "pp5002260206", "name": "Kettle", "description": "Russell Hobbs Brushed Steel Kettle 1.7Ltr", "quantity": "1", "price": 30.99, "category": 11, "rating": 4.7, "image_url": "http://s7d9.scene7.com/is/image/JCPenney/DP0624201520422666C.tif?hei=380&amp;wid=380&op_usm=.4,.8,0,0&resmode=sharp2&op_usm=1.5,.8,0,0&resmode=sharp", "image": "kettle.jpg"}}, 
    {"pk": 7, "model": "products.product", "fields": {"sku": "pp5002440521", "name": "Suma Grill D9 Oven & Grill Cleaner", "description": "Suma D9 Oven and Grill Cleaner is a highly alkali detergent suitable for periodic cleaning of heavily soiled ovens, grills and fryers.", "quantity": "6", "price": 16.99, "category": 7, "rating": 3.0, "image_url": "http://s7d9.scene7.com/is/image/JCPenney/DP0226201317034754M.tif?hei=380&amp;wid=380&op_usm=.4,.8,0,0&resmode=sharp2&op_usm=1.5,.8,0,0&resmode=sharp", "image": "d9.jpg"}}, 
    {"pk": 8, "model": "products.product", "fields": {"sku": "pp5002601115", "name": "Blue Roll", "description": "Fast Supplies 2 Ply Centrefeed Roll Blue 150m", "quantity": "6", "price": 9.99, "category": 12, "rating": 4.6, "image_url": "http://s7d2.scene7.com/is/image/JCPenney/DP0926201317071162M.tif?wid=65&hei=65&fmt=jpg&op_usm=.4,.8,0,0&resmode=sharp2", "image": "blue_roll.jpg"}}, 
    {"pk": 9, "model": "products.product", "fields": {"sku": "pp5002690715", "name": "Hair Dryer", "description": "High endurance professional dryer with a long-life and powerful 2000W AC motor perfect for a demanding professional environment. Features 3 heat settings, 2 speed settings and an instant cold shot button for total styling control. Features: - 2000W AC motor - 3 heat & 2 speed settings - cold shot button - slim concentrator nozzle - removable rear filter - salon length 2.7m cord with hanging loop 6 months Warranty", "quantity": "1", "price": 28.99, "category": 11, "rating": 4.6, "image_url": "http://s7d2.scene7.com/is/image/JCPenney/DP1020201517025390M.tif?wid=65&hei=65&fmt=jpg&op_usm=.4,.8,0,0&resmode=sharp2", "image": "hairdryer.jpg"}}, 
    {"pk": 10, "model": "products.product", "fields": {"sku": "pp5002701115", "name": "Urinal Blocks", "description": "Non hazardous urinal blocks that counteracts urine malodours leaving a hygienically clean smell", "quantity": "1", "price": 33.99, "category": 2, "rating": 5.0, "image_url": "http://s7d2.scene7.com/is/image/JCPenney/DP0418201317011949M.tif?wid=65&hei=65&fmt=jpg&op_usm=.4,.8,0,0&resmode=sharp2", "image": "urinal_block.jpg"}}, 
    {"pk": 11, "model": "products.product", "fields": {"sku": "pp5002761055", "name": "Water Glass", "description": "Allegra Water Glass 44cl (15.5oz)", "quantity": "24", "price": 59.99, "category": 4, "rating": 4.4, "image_url": "http://s7d2.scene7.com/is/image/JCPenney/0900631B81B0C2D9M.tif?wid=65&hei=65&fmt=jpg&op_usm=.4,.8,0,0&resmode=sharp2", "image": "water_glass.jpg"}}, 
    {"pk": 12, "model": "products.product", "fields": {"sku": "pp5002820069", "name": "Fairy Platinum Dishwasher Tablets", "description": "Fairy Platinum Dishwasher Tablets", "quantity": "1", "price": 35.99, "category": 8, "rating": 4.3, "image_url": "http://s7d2.scene7.com/is/image/JCPenney/DP0510201317010521M.tif?wid=65&hei=65&fmt=jpg&op_usm=.4,.8,0,0&resmode=sharp2", "image": "dishwash_tablets.jpg"}},
    {"pk": 13, "model": "products.product", "fields": {"sku": "pp5002820070", "name": "Cif Cream Cleaner White", "description": "Cif Cream Cleaner White", "quantity": "8", "price": 11.99, "category": 3, "rating": 4.5, "image_url": "http://s7d2.scene7.com/is/image/JCPenney/DP0510201317010521M.tif?wid=65&hei=65&fmt=jpg&op_usm=.4,.8,0,0&resmode=sharp2", "image": "cif.jpg"}},
    {"pk": 14, "model": "products.product", "fields": {"sku": "pp5002820071", "name": "White Chef Jacket", "description": "Chefs Jacket S/S Stud Front White Medium/38-40", "quantity": "1", "price": 11.99, "category": 4, "rating": 3.5, "image_url": "http://s7d2.scene7.com/is/image/JCPenney/DP0510201317010521M.tif?wid=65&hei=65&fmt=jpg&op_usm=.4,.8,0,0&resmode=sharp2", "image": "chef_jacket.jpg"}},
    {"pk": 15, "model": "products.product", "fields": {"sku": "pp5002820072", "name": "Pledge Wood Polish", "description": "Pledge Amazing Shine Wood Polish 12 x 400ml", "quantity": "12", "price": 19.99, "category": 5, "rating": 3.5, "image_url": "http://s7d2.scene7.com/is/image/JCPenney/DP0510201317010521M.tif?wid=65&hei=65&fmt=jpg&op_usm=.4,.8,0,0&resmode=sharp2", "image": "wood_polish.jpg"}},
    {"pk": 16, "model": "products.product", "fields": {"sku": "pp5002820073", "name": "White Plate 26.8cm", "description": "Alchemy White Plate 26.8cm", "quantity": "12", "price": 89.99, "category": 6, "rating": 3.9, "image_url": "http://s7d2.scene7.com/is/image/JCPenney/DP0510201317010521M.tif?wid=65&hei=65&fmt=jpg&op_usm=.4,.8,0,0&resmode=sharp2", "image": "main_plate.jpg"}},
    {"pk": 17, "model": "products.product", "fields": {"sku": "pp5002820074", "name": "White Plate 16.5cm", "description": "Alchemy White Plate 16.5cm", "quantity": "12", "price": 59.99, "category": 6, "rating": 4.0, "image_url": "http://s7d2.scene7.com/is/image/JCPenney/DP0510201317010521M.tif?wid=65&hei=65&fmt=jpg&op_usm=.4,.8,0,0&resmode=sharp2", "image": "side_plate.jpg"}},
    {"pk": 18, "model": "products.product", "fields": {"sku": "pp5002820075", "name": "Chrome Plated Automatic Hot Air Hand Dryer", "description": "FEATURES Infra-red sensor - no touch Rated power:2500w (10.8A) IPX1 rated Class 1 rated isolation Airspeed: 30 m/s Sound level: 85 ± 3 db 360º revolving nozzle Durable metal construction - vandal resistant Voltage: 220/240v (50Hz) Air movement volume:270m3/hour 2 year manufacturer's warranty", "quantity": "1", "price": 169.99, "category": 12, "rating": 4.4, "image_url": "http://s7d2.scene7.com/is/image/JCPenney/DP0510201317010521M.tif?wid=65&hei=65&fmt=jpg&op_usm=.4,.8,0,0&resmode=sharp2", "image": "hand_dryer.jpg"}},
    {"pk": 19, "model": "products.product", "fields": {"sku": "pp5002820076", "name": "InnuScience Nu-Action 3 Conc. Degreaser", "description": "InnuScience Nu-Action 3 Conc. Degreaser", "quantity": "1", "price": 24.99, "category": 7, "rating": 4.9, "image_url": "http://s7d2.scene7.com/is/image/JCPenney/DP0510201317010521M.tif?wid=65&hei=65&fmt=jpg&op_usm=.4,.8,0,0&resmode=sharp2", "image": "degreaser.jpg"}},
    {"pk": 20, "model": "products.product", "fields": {"sku": "pp5002820077", "name": "Suma D10 Disinfectant", "description": "D10 Suma Bac All Purpose Cleaner Disinfectant", "quantity": "1", "price": 21.99, "category": 5, "rating": 4.4, "image_url": "http://s7d2.scene7.com/is/image/JCPenney/DP0510201317010521M.tif?wid=65&hei=65&fmt=jpg&op_usm=.4,.8,0,0&resmode=sharp2", "image": "d10.jpg"}},
    {"pk": 21, "model": "products.product", "fields": {"sku": "pp5002820078", "name": "Ice Bucket 10ltr", "description": "Brushed Aluminium Effect Ice bucket 10L", "quantity": "1", "price": 24.99, "category": 3, "rating": 4.0, "image_url": "http://s7d2.scene7.com/is/image/JCPenney/DP0510201317010521M.tif?wid=65&hei=65&fmt=jpg&op_usm=.4,.8,0,0&resmode=sharp2", "image": "ice_bucket.jpg"}},
    {"pk": 22, "model": "products.product", "fields": {"sku": "pp5002820079", "name": "Iron", "description": "Dry Iron 1200W White/Blue Non-Stick Sole Plate", "quantity": "1", "price": 33.99, "category": 11, "rating": 4.4, "image_url": "http://s7d2.scene7.com/is/image/JCPenney/DP0510201317010521M.tif?wid=65&hei=65&fmt=jpg&op_usm=.4,.8,0,0&resmode=sharp2", "image": "iron.jpg"}},
    {"pk": 23, "model": "products.product", "fields": {"sku": "pp5002820080", "name": "Teaspoon", "description": "Brushed Aluminium Effect Ice bucket 10L", "quantity": "12", "price": 7.99, "category": 9, "rating": 4.6, "image_url": "http://s7d2.scene7.com/is/image/JCPenney/DP0510201317010521M.tif?wid=65&hei=65&fmt=jpg&op_usm=.4,.8,0,0&resmode=sharp2", "image": "teaspoon.jpg"}},
    {"pk": 24, "model": "products.product", "fields": {"sku": "pp5002820081", "name": "Wine Glass 20.5oz Clear", "description": "Utopia Nude Reserva Wine Glass 20.5oz Clear", "quantity": "12", "price": 52.99, "category": 10, "rating": 4.7, "image_url": "http://s7d2.scene7.com/is/image/JCPenney/DP0510201317010521M.tif?wid=65&hei=65&fmt=jpg&op_usm=.4,.8,0,0&resmode=sharp2", "image": "wine_glass.jpg"}}
]